{
  "date": "20260617",
  "as_of": "2026-06-17 13:22 KST",
  "bets": [
    {
      "code": "402340",
      "ticker": "SK스퀘어",
      "entry": 1593000.0,
      "target": 1672650,
      "raw": 78,
      "prob": "78%"
    },
    {
      "code": "095610",
      "ticker": "테스",
      "entry": 167300.0,
      "target": 175665,
      "raw": 78,
      "prob": "78%"
    },
    {
      "code": "319660",
      "ticker": "피에스케이",
      "entry": 159300.0,
      "target": 167265,
      "raw": 77,
      "prob": "77%"
    },
    {
      "code": "034730",
      "ticker": "SK",
      "entry": 693000.0,
      "target": 727650,
      "raw": 77,
      "prob": "77%"
    },
    {
      "code": "001820",
      "ticker": "삼화콘덴서",
      "entry": 148400.0,
      "target": 155820,
      "raw": 75,
      "prob": "75%"
    }
  ]
}