{
  "date": "20260622",
  "as_of": "2026-06-22 12:52 KST",
  "bets": [
    {
      "code": "028260",
      "ticker": "삼성물산",
      "entry": 531000.0,
      "target": 557550,
      "raw": 95,
      "prob": "95%"
    },
    {
      "code": "093370",
      "ticker": "후성",
      "entry": 19530.0,
      "target": 20506,
      "raw": 95,
      "prob": "95%"
    },
    {
      "code": "402340",
      "ticker": "SK스퀘어",
      "entry": 1943000.0,
      "target": 2040150,
      "raw": 68,
      "prob": "68%"
    },
    {
      "code": "000990",
      "ticker": "DB하이텍",
      "entry": 164900.0,
      "target": 173145,
      "raw": 63,
      "prob": "63%"
    },
    {
      "code": "066570",
      "ticker": "LG전자",
      "entry": 235000.0,
      "target": 246750,
      "raw": 62,
      "prob": "62%"
    }
  ]
}