{
  "as_of": "2026-06-10 13:22 KST",
  "intraday_rank": [
    {
      "ticker": "신세계",
      "code": "004170",
      "tomorrow_up_prob": "90%",
      "entry": 682000.0,
      "target": 716100,
      "stop": 661540,
      "confidence": "상",
      "reasons": [
        "강세마감(0.85)",
        "정배열",
        "MACD강세"
      ],
      "risk": "특이 위험 낮음",
      "day_change": 7.05,
      "cause_news": [
        {
          "title": "[투데이's 특징주] 신세계, 외국인 관광객 증가 수혜 기대감에 장 초반...",
          "url": "https://www.todaykorea.co.kr/news/articleView.html?idxno=402525",
          "office": "todaykorea",
          "sentiment": "호재",
          "cause_score": 17,
          "cause_reason": "제목 언급, 주어, 원인표현, 인과표현, 재료, 검색맥락, 당일"
        },
        {
          "title": "[특징주] 신세계, 中 관광객 증가·백화점 호조 기대에 6%대 상승",
          "url": "https://biz.chosun.com/stock/stock_general/2026/06/10/3G5CZH5LD5CQBD2J2G4XZLKXJQ/?utm_source=naver&utm_medium=original&utm_campaign=biz",
          "office": "biz",
          "sentiment": "호재",
          "cause_score": 13,
          "cause_reason": "제목 언급, 주어, 원인표현, 재료, 검색맥락, 당일"
        },
        {
          "title": "신세계 주가 장중 9%대 올라, 매출 증가 기대감 속 백화점주 강세",
          "url": "https://www.businesspost.co.kr/BP?command=article_view&num=439660",
          "office": "businesspost",
          "sentiment": "호재",
          "cause_score": 11,
          "cause_reason": "제목 언급, 주어, 원인표현, 검색맥락, 당일"
        }
      ],
      "cause_confidence": "높음",
      "cause_summary": "[투데이's 특징주] 신세계, 외국인 관광객 증가 수혜 기대감에 장 초반..."
    },
    {
      "ticker": "후성",
      "code": "093370",
      "tomorrow_up_prob": "88%",
      "entry": 16120.0,
      "target": 16926,
      "stop": 15636,
      "confidence": "상",
      "reasons": [
        "강세마감(0.81)",
        "정배열",
        "MACD강세"
      ],
      "risk": "특이 위험 낮음",
      "day_change": 19.23,
      "cause_news": [
        {
          "title": "후성 주가 급등세…수차례 VI 발동하기도",
          "url": "https://www.cbci.co.kr/news/articleView.html?idxno=580910",
          "office": "cbci",
          "sentiment": "호재",
          "cause_score": 13,
          "cause_reason": "제목 언급, 주어, 원인표현, 재료, 검색맥락, 당일"
        },
        {
          "title": "[특징주] 후성, 1분기 실적 선방에도 약세…2분기 LiPF6·반도체가스 개...",
          "url": "https://www.tokenpost.kr/news/economy/360710",
          "office": "tokenpost",
          "sentiment": "호재",
          "cause_score": 7,
          "cause_reason": "제목 언급, 주어, 원인표현, 재료, 검색맥락, 오래됨"
        },
        {
          "title": "[특징주] 후성, 1분기 실적 발표...향후 분기별 사업 전망",
          "url": "https://www.newstnt.com/news/articleView.html?idxno=702866",
          "office": "newstnt",
          "sentiment": "호재",
          "cause_score": 7,
          "cause_reason": "제목 언급, 주어, 원인표현, 재료, 검색맥락, 오래됨"
        }
      ],
      "cause_confidence": "높음",
      "cause_summary": "후성 주가 급등세…수차례 VI 발동하기도"
    },
    {
      "ticker": "NAVER",
      "code": "035420",
      "tomorrow_up_prob": "78%",
      "entry": 231000.0,
      "target": 242550,
      "stop": 224070,
      "confidence": "상",
      "reasons": [
        "정배열",
        "MACD강세",
        "RSI50.4 강세"
      ],
      "risk": "약한 마감",
      "day_change": -10.89,
      "cause_news": [
        {
          "title": "[특징주] 네이버, 엔비디아 협력 기대 하루 만에 꺾였다…차익실현에 1...",
          "url": "https://www.tokenpost.kr/news/economy/367307",
          "office": "tokenpost",
          "sentiment": "호재",
          "cause_score": 15,
          "cause_reason": "제목 언급, 주어, 원인표현, 인과표현, 재료, 검색맥락"
        },
        {
          "title": "[특징주] 네이버, 엔비디아 협력 발표 뒤 차익실현에 '급락'",
          "url": "https://www.g-enews.com/view.php?ud=20260609095656477744093b5d4e_1",
          "office": "g-enews",
          "sentiment": "악재",
          "cause_score": 8,
          "cause_reason": "제목 언급, 주어, 원인표현, 재료, 검색맥락, 악재"
        },
        {
          "title": "[ET특징주] 젠슨 황 출국과 함께… LG전자·네이버 주가 하락",
          "url": "https://www.etnews.com/20260609000187",
          "office": "etnews",
          "sentiment": "악재",
          "cause_score": 6,
          "cause_reason": "제목 언급, 원인표현, 재료, 검색맥락, 악재"
        }
      ],
      "cause_confidence": "높음",
      "cause_summary": "[특징주] 네이버, 엔비디아 협력 기대 하루 만에 꺾였다…차익실현에 1..."
    },
    {
      "ticker": "SK이터닉스",
      "code": "475150",
      "tomorrow_up_prob": "74%",
      "entry": 44350.0,
      "target": 46568,
      "stop": 43020,
      "confidence": "상",
      "reasons": [
        "강세마감(1.0)",
        "RSI51.9 강세",
        "거래량2.75배"
      ],
      "risk": "특이 위험 낮음",
      "day_change": 29.87,
      "cause_news": [
        {
          "title": "[특징주] SK이터닉스, 신재생에너지 사업 재편 소식에 상한가",
          "url": "https://www.ajunews.com/view/20260610113207436",
          "office": "ajunews",
          "sentiment": "호재",
          "cause_score": 15,
          "cause_reason": "제목 언급, 주어, 원인표현, 인과표현, 검색맥락, 당일"
        },
        {
          "title": "[ET특징주] SK이터닉스, 신재생에너지 사업 재편 기대감에 주가 上",
          "url": "https://www.etnews.com/20260610000192",
          "office": "etnews",
          "sentiment": "호재",
          "cause_score": 15,
          "cause_reason": "제목 언급, 주어, 원인표현, 인과표현, 검색맥락, 당일"
        },
        {
          "title": "[특징주] SK이터닉스, 신재생에너지주 오름세 속 +29.87% 上 기록",
          "url": "https://www.jeonmae.co.kr/news/articleView.html?idxno=1263919",
          "office": "jeonmae",
          "sentiment": "호재",
          "cause_score": 13,
          "cause_reason": "제목 언급, 주어, 원인표현, 재료, 검색맥락, 당일"
        }
      ],
      "cause_confidence": "높음",
      "cause_summary": "[특징주] SK이터닉스, 신재생에너지 사업 재편 소식에 상한가"
    },
    {
      "ticker": "화신정공",
      "code": "126640",
      "tomorrow_up_prob": "72%",
      "entry": 4430.0,
      "target": 4652,
      "stop": 4297,
      "confidence": "상",
      "reasons": [
        "강세마감(1.0)",
        "정배열",
        "MACD강세"
      ],
      "risk": "RSI90.2 과매수, Stoch 과매수",
      "day_change": 29.91,
      "cause_news": [
        {
          "title": "[특징주] 화신정공, 보스턴다이나믹스 '아틀라스' 공급망 편입 기대감에...",
          "url": "https://www.widedaily.com/news/articleView.html?idxno=295327",
          "office": "widedaily",
          "sentiment": "호재",
          "cause_score": 15,
          "cause_reason": "제목 언급, 주어, 원인표현, 인과표현, 재료, 검색맥락"
        },
        {
          "title": "화신정공, 투자주의종목 지정→주가 급등에 투자경보",
          "url": "https://www.topstarnews.net/news/articleView.html?idxno=16085251",
          "office": "topstarnews",
          "sentiment": "호재",
          "cause_score": 13,
          "cause_reason": "제목 언급, 주어, 원인표현, 재료, 검색맥락, 당일"
        },
        {
          "title": "화신정공, 투자경고종목 지정예고→주가 급등세 주의 요망",
          "url": "https://www.topstarnews.net/news/articleView.html?idxno=16085242",
          "office": "topstarnews",
          "sentiment": "호재",
          "cause_score": 13,
          "cause_reason": "제목 언급, 주어, 원인표현, 재료, 검색맥락, 당일"
        }
      ],
      "cause_confidence": "높음",
      "cause_summary": "[특징주] 화신정공, 보스턴다이나믹스 '아틀라스' 공급망 편입 기대감에..."
    },
    {
      "ticker": "제주은행",
      "code": "006220",
      "tomorrow_up_prob": "71%",
      "entry": 13050.0,
      "target": 13702,
      "stop": 12658,
      "confidence": "상",
      "reasons": [
        "강세마감(0.89)",
        "RSI65.5 강세",
        "거래량5.65배"
      ],
      "risk": "특이 위험 낮음",
      "day_change": null,
      "related_news": [
        {
          "title": "고객 상담 넘어 업무 혁신으로… 제주은행, AI 은행 전환 속도",
          "url": "https://n.news.naver.com/mnews/article/661/0000077807",
          "office": "JIBS",
          "sentiment": "호재"
        }
      ]
    },
    {
      "ticker": "현대건설",
      "code": "000720",
      "tomorrow_up_prob": "68%",
      "entry": 132100.0,
      "target": 138705,
      "stop": 128137,
      "confidence": "중",
      "reasons": [
        "강세마감(0.94)",
        "Stoch골든",
        "호재"
      ],
      "risk": "특이 위험 낮음",
      "day_change": null,
      "cause_news": [
        {
          "title": "현대건설, 7%대 급등…5000억 조달해 미래 에너지 사업 확대",
          "url": "http://www.econonews.co.kr/news/articleView.html?idxno=439502",
          "office": "econonews",
          "sentiment": "호재",
          "cause_score": 13,
          "cause_reason": "제목 언급, 주어, 원인표현, 재료, 검색맥락, 당일"
        },
        {
          "title": "[주요공시] 삼성전자, 팸텍, 하나기술, 현대건설, 하이로닉, SKC, 소룩스...",
          "url": "https://www.kdpress.co.kr/news/articleView.html?idxno=205979",
          "office": "kdpress",
          "sentiment": "호재",
          "cause_score": 7,
          "cause_reason": "제목 언급, 주어, 재료, 일반뉴스, 당일"
        }
      ],
      "cause_confidence": "높음",
      "cause_summary": "현대건설, 7%대 급등…5000억 조달해 미래 에너지 사업 확대"
    },
    {
      "ticker": "SK오션플랜트",
      "code": "100090",
      "tomorrow_up_prob": "66%",
      "entry": 17440.0,
      "target": 18312,
      "stop": 16917,
      "confidence": "중",
      "reasons": [
        "Stoch골든",
        "거래량6.34배",
        "호재"
      ],
      "risk": "특이 위험 낮음",
      "day_change": 16.44,
      "cause_news": [
        {
          "title": "SK이터닉스·SK오션플랜트, SK그룹 신재생 사업 재편 기대감에 동반 강세...",
          "url": "https://www.newsway.co.kr/news/view?ud=2026061010000321317",
          "office": "newsway",
          "sentiment": "호재",
          "cause_score": 15,
          "cause_reason": "제목 언급, 주어, 원인표현, 인과표현, 검색맥락, 당일"
        },
        {
          "title": "SK오션플랜트 주가, 6월 10일 장중 16,700원 14.86% 상승",
          "url": "https://www.topstarnews.net/news/articleView.html?idxno=16086014",
          "office": "topstarnews",
          "sentiment": "호재",
          "cause_score": 5,
          "cause_reason": "제목 언급, 주어, 일반뉴스, 당일"
        }
      ],
      "cause_confidence": "높음",
      "cause_summary": "SK이터닉스·SK오션플랜트, SK그룹 신재생 사업 재편 기대감에 동반 강세..."
    },
    {
      "ticker": "케이뱅크",
      "code": "279570",
      "tomorrow_up_prob": "63%",
      "entry": 6340.0,
      "target": 6657,
      "stop": 6150,
      "confidence": "중",
      "reasons": [
        "RSI63.3 강세",
        "거래량6.69배",
        "호재"
      ],
      "risk": "특이 위험 낮음",
      "day_change": 12.28,
      "cause_news": [
        {
          "title": "케이뱅크 주가, 강세... 외인·기관 쌍끌이 매수",
          "url": "https://www.ggilbo.com/news/articleView.html?idxno=1162859",
          "office": "ggilbo",
          "sentiment": "악재",
          "cause_score": 8,
          "cause_reason": "제목 언급, 주어, 원인표현, 검색맥락, 악재, 당일"
        }
      ],
      "cause_confidence": "높음",
      "cause_summary": "케이뱅크 주가, 강세... 외인·기관 쌍끌이 매수"
    },
    {
      "ticker": "노타",
      "code": "486990",
      "tomorrow_up_prob": "54%",
      "entry": 27250.0,
      "target": 28612,
      "stop": 26432,
      "confidence": "하",
      "reasons": [
        "호재",
        "장중 18회 지속"
      ],
      "risk": "약한 마감",
      "day_change": -10.1,
      "related_news": [
        {
          "title": "디든·노타·에이로봇 등 총출동…젠슨 황 &quot;韓스타트업 선물은 '이것'...",
          "url": "https://n.news.naver.com/mnews/article/421/0008992442",
          "office": "뉴스1",
          "sentiment": "호재"
        },
        {
          "title": "노타, 엔비디아 아태 파트너데이 ‘한국 유일’ 패널 참여…“피지컬...",
          "url": "https://n.news.naver.com/mnews/article/018/0006295755",
          "office": "이데일리",
          "sentiment": "호재"
        },
        {
          "title": "노타, 영상관제 AI 현장 적용 확대…엔비디아와 협력",
          "url": "https://n.news.naver.com/mnews/article/003/0013979735",
          "office": "뉴시스",
          "sentiment": "호재"
        }
      ]
    }
  ],
  "closing_bet": [
    {
      "ticker": "신세계",
      "code": "004170",
      "tomorrow_up_prob": "90%",
      "entry": 682000.0,
      "target": 716100,
      "stop": 661540,
      "confidence": "상",
      "reasons": [
        "강세마감(0.85)",
        "정배열",
        "MACD강세"
      ],
      "risk": "특이 위험 낮음",
      "day_change": 7.05,
      "cause_news": [
        {
          "title": "[투데이's 특징주] 신세계, 외국인 관광객 증가 수혜 기대감에 장 초반...",
          "url": "https://www.todaykorea.co.kr/news/articleView.html?idxno=402525",
          "office": "todaykorea",
          "sentiment": "호재",
          "cause_score": 17,
          "cause_reason": "제목 언급, 주어, 원인표현, 인과표현, 재료, 검색맥락, 당일"
        },
        {
          "title": "[특징주] 신세계, 中 관광객 증가·백화점 호조 기대에 6%대 상승",
          "url": "https://biz.chosun.com/stock/stock_general/2026/06/10/3G5CZH5LD5CQBD2J2G4XZLKXJQ/?utm_source=naver&utm_medium=original&utm_campaign=biz",
          "office": "biz",
          "sentiment": "호재",
          "cause_score": 13,
          "cause_reason": "제목 언급, 주어, 원인표현, 재료, 검색맥락, 당일"
        },
        {
          "title": "신세계 주가 장중 9%대 올라, 매출 증가 기대감 속 백화점주 강세",
          "url": "https://www.businesspost.co.kr/BP?command=article_view&num=439660",
          "office": "businesspost",
          "sentiment": "호재",
          "cause_score": 11,
          "cause_reason": "제목 언급, 주어, 원인표현, 검색맥락, 당일"
        }
      ],
      "cause_confidence": "높음",
      "cause_summary": "[투데이's 특징주] 신세계, 외국인 관광객 증가 수혜 기대감에 장 초반..."
    },
    {
      "ticker": "후성",
      "code": "093370",
      "tomorrow_up_prob": "88%",
      "entry": 16120.0,
      "target": 16926,
      "stop": 15636,
      "confidence": "상",
      "reasons": [
        "강세마감(0.81)",
        "정배열",
        "MACD강세"
      ],
      "risk": "특이 위험 낮음",
      "day_change": 19.23,
      "cause_news": [
        {
          "title": "후성 주가 급등세…수차례 VI 발동하기도",
          "url": "https://www.cbci.co.kr/news/articleView.html?idxno=580910",
          "office": "cbci",
          "sentiment": "호재",
          "cause_score": 13,
          "cause_reason": "제목 언급, 주어, 원인표현, 재료, 검색맥락, 당일"
        },
        {
          "title": "[특징주] 후성, 1분기 실적 선방에도 약세…2분기 LiPF6·반도체가스 개...",
          "url": "https://www.tokenpost.kr/news/economy/360710",
          "office": "tokenpost",
          "sentiment": "호재",
          "cause_score": 7,
          "cause_reason": "제목 언급, 주어, 원인표현, 재료, 검색맥락, 오래됨"
        },
        {
          "title": "[특징주] 후성, 1분기 실적 발표...향후 분기별 사업 전망",
          "url": "https://www.newstnt.com/news/articleView.html?idxno=702866",
          "office": "newstnt",
          "sentiment": "호재",
          "cause_score": 7,
          "cause_reason": "제목 언급, 주어, 원인표현, 재료, 검색맥락, 오래됨"
        }
      ],
      "cause_confidence": "높음",
      "cause_summary": "후성 주가 급등세…수차례 VI 발동하기도"
    },
    {
      "ticker": "NAVER",
      "code": "035420",
      "tomorrow_up_prob": "78%",
      "entry": 231000.0,
      "target": 242550,
      "stop": 224070,
      "confidence": "상",
      "reasons": [
        "정배열",
        "MACD강세",
        "RSI50.4 강세"
      ],
      "risk": "약한 마감",
      "day_change": -10.89,
      "cause_news": [
        {
          "title": "[특징주] 네이버, 엔비디아 협력 기대 하루 만에 꺾였다…차익실현에 1...",
          "url": "https://www.tokenpost.kr/news/economy/367307",
          "office": "tokenpost",
          "sentiment": "호재",
          "cause_score": 15,
          "cause_reason": "제목 언급, 주어, 원인표현, 인과표현, 재료, 검색맥락"
        },
        {
          "title": "[특징주] 네이버, 엔비디아 협력 발표 뒤 차익실현에 '급락'",
          "url": "https://www.g-enews.com/view.php?ud=20260609095656477744093b5d4e_1",
          "office": "g-enews",
          "sentiment": "악재",
          "cause_score": 8,
          "cause_reason": "제목 언급, 주어, 원인표현, 재료, 검색맥락, 악재"
        },
        {
          "title": "[ET특징주] 젠슨 황 출국과 함께… LG전자·네이버 주가 하락",
          "url": "https://www.etnews.com/20260609000187",
          "office": "etnews",
          "sentiment": "악재",
          "cause_score": 6,
          "cause_reason": "제목 언급, 원인표현, 재료, 검색맥락, 악재"
        }
      ],
      "cause_confidence": "높음",
      "cause_summary": "[특징주] 네이버, 엔비디아 협력 기대 하루 만에 꺾였다…차익실현에 1..."
    },
    {
      "ticker": "SK이터닉스",
      "code": "475150",
      "tomorrow_up_prob": "74%",
      "entry": 44350.0,
      "target": 46568,
      "stop": 43020,
      "confidence": "상",
      "reasons": [
        "강세마감(1.0)",
        "RSI51.9 강세",
        "거래량2.75배"
      ],
      "risk": "특이 위험 낮음",
      "day_change": 29.87,
      "cause_news": [
        {
          "title": "[특징주] SK이터닉스, 신재생에너지 사업 재편 소식에 상한가",
          "url": "https://www.ajunews.com/view/20260610113207436",
          "office": "ajunews",
          "sentiment": "호재",
          "cause_score": 15,
          "cause_reason": "제목 언급, 주어, 원인표현, 인과표현, 검색맥락, 당일"
        },
        {
          "title": "[ET특징주] SK이터닉스, 신재생에너지 사업 재편 기대감에 주가 上",
          "url": "https://www.etnews.com/20260610000192",
          "office": "etnews",
          "sentiment": "호재",
          "cause_score": 15,
          "cause_reason": "제목 언급, 주어, 원인표현, 인과표현, 검색맥락, 당일"
        },
        {
          "title": "[특징주] SK이터닉스, 신재생에너지주 오름세 속 +29.87% 上 기록",
          "url": "https://www.jeonmae.co.kr/news/articleView.html?idxno=1263919",
          "office": "jeonmae",
          "sentiment": "호재",
          "cause_score": 13,
          "cause_reason": "제목 언급, 주어, 원인표현, 재료, 검색맥락, 당일"
        }
      ],
      "cause_confidence": "높음",
      "cause_summary": "[특징주] SK이터닉스, 신재생에너지 사업 재편 소식에 상한가"
    },
    {
      "ticker": "화신정공",
      "code": "126640",
      "tomorrow_up_prob": "72%",
      "entry": 4430.0,
      "target": 4652,
      "stop": 4297,
      "confidence": "상",
      "reasons": [
        "강세마감(1.0)",
        "정배열",
        "MACD강세"
      ],
      "risk": "RSI90.2 과매수, Stoch 과매수",
      "day_change": 29.91,
      "cause_news": [
        {
          "title": "[특징주] 화신정공, 보스턴다이나믹스 '아틀라스' 공급망 편입 기대감에...",
          "url": "https://www.widedaily.com/news/articleView.html?idxno=295327",
          "office": "widedaily",
          "sentiment": "호재",
          "cause_score": 15,
          "cause_reason": "제목 언급, 주어, 원인표현, 인과표현, 재료, 검색맥락"
        },
        {
          "title": "화신정공, 투자주의종목 지정→주가 급등에 투자경보",
          "url": "https://www.topstarnews.net/news/articleView.html?idxno=16085251",
          "office": "topstarnews",
          "sentiment": "호재",
          "cause_score": 13,
          "cause_reason": "제목 언급, 주어, 원인표현, 재료, 검색맥락, 당일"
        },
        {
          "title": "화신정공, 투자경고종목 지정예고→주가 급등세 주의 요망",
          "url": "https://www.topstarnews.net/news/articleView.html?idxno=16085242",
          "office": "topstarnews",
          "sentiment": "호재",
          "cause_score": 13,
          "cause_reason": "제목 언급, 주어, 원인표현, 재료, 검색맥락, 당일"
        }
      ],
      "cause_confidence": "높음",
      "cause_summary": "[특징주] 화신정공, 보스턴다이나믹스 '아틀라스' 공급망 편입 기대감에..."
    }
  ],
  "disclaimer": "예측·투자 참고용이며 매수 추천이 아닙니다. 갭 리스크가 있으니 손절을 지키세요.",
  "backtest": {
    "sample": 25,
    "recent_hit_rate": "36% (n=25)",
    "avg_return": -3.4,
    "target_rate": "60%"
  }
}